LICENSE
MANIFEST.in
README.rst
requirements.txt
setup.cfg
setup.py
ckanext/__init__.py
ckanext/ddkids/__init__.py
ckanext/ddkids/plugin.py
ckanext/ddkids/harvesters/__init__.py
ckanext/ddkids/harvesters/harvester.py
ckanext/ddkids/harvesters/import_finder.py
ckanext/ddkids/harvesters/metadata_reader.py
ckanext/ddkids/public/ddkids_overrides.css
ckanext/ddkids/templates/base.html
ckanext/ddkids/templates/drupal_footer.html
ckanext/ddkids/templates/drupal_header.html
ckanext/ddkids/templates/footer.html
ckanext/ddkids/templates/header.html
ckanext/ddkids/templates/datatables/datatables_view.html
ckanext/ddkids/templates/package/base.html
ckanext/ddkids/templates/package/read_base.html
ckanext/ddkids/templates/package/resource_read.html
ckanext/ddkids/templates/package/search.html
ckanext/ddkids/templates/package/snippets/additional_info.html
ckanext/ddkids/templates/package/snippets/info.html
ckanext/ddkids/templates/package/snippets/package_basic_fields.html
ckanext/ddkids/templates/package/snippets/package_metadata_fields.html
ckanext/ddkids/templates/package/snippets/resource_item.html
ckanext/ddkids/templates/package/snippets/resource_view_filters.html
ckanext/ddkids/templates/package/snippets/resources_list.html
ckanext/ddkids/templates/package/snippets/tags.html
ckanext/ddkids/templates/snippets/facet_list.html
ckanext/ddkids/templates/snippets/group_item.html
ckanext/ddkids/templates/snippets/home_breadcrumb_item.html
ckanext/ddkids/templates/snippets/local_friendly_datetime.html
ckanext/ddkids/templates/snippets/package_item.html
ckanext/ddkids/templates/snippets/tag_list.html
ckanext/ddkids/tests/__init__.py
ckanext/ddkids/tests/test_plugin.py
ckanext_ddkids.egg-info/PKG-INFO
ckanext_ddkids.egg-info/SOURCES.txt
ckanext_ddkids.egg-info/dependency_links.txt
ckanext_ddkids.egg-info/entry_points.txt
ckanext_ddkids.egg-info/namespace_packages.txt
ckanext_ddkids.egg-info/top_level.txt