Metadata-Version: 1.1
Name: ckanext-ddkids
Version: 0.0.2
Summary: DDKids Site Customizations
Home-page: https://github.com/Velir/ckanext-ddkids
Author: Velir
Author-email: info@velir.com
License: AGPL
Keywords: CKAN
Platform: UNKNOWN
Classifier: Development Status :: 4 - Beta
Classifier: License :: OSI Approved :: GNU Affero General Public License v3 or later (AGPLv3+)
Classifier: Programming Language :: Python :: 2.7
